{"stats":{"minecraft:picked_up":{"minecraft:sandstone":1,"minecraft:gravel":30,"exposure:developed_black_and_white_film":1,"minecraft:flint":1,"minecraft:sand":11,"minecraft:white_dye":63,"minecraft:red_banner":1,"minecraft:string":1,"minecraft:paper":63,"minecraft:black_dye":63,"minecraft:orange_terracotta":1,"minecraft:yellow_banner":1,"minecraft:red_sand":1,"minecraft:cobbled_deepslate":4,"create:ochrum":7,"minecraft:granite":1,"create:veridium":1,"create:shaft":2,"minecraft:emerald":1,"minecraft:glass_bottle":2,"minecraft:cobblestone":53},"minecraft:crafted":{"exposure:developed_black_and_white_film":2},"minecraft:dropped":{"minecraft:ice":1,"create:veridium":1,"create:shaft":2,"minecraft:orange_terracotta":1,"minecraft:red_banner":80,"dehydration:netherite_leather_flask":1,"minecraft:emerald":1},"minecraft:used":{"create:track":3,"farmersdelight:honey_cookie":5,"minecraft:water_bucket":3,"dehydration:purified_water_bucket":1,"minecraft:writable_book":8,"minecraft:barrier":41,"minecraft:spawner":6,"minecraft:cactus":1,"exposure:lightroom":3,"simpleradio:speaker":18,"simpleradio:radiosmither":6,"simpleradio:radio":10,"scorchful:cactus_juice":3,"minecraft:bedrock":42,"create:spout":1,"minecraft:glow_item_frame":1,"dehydration:netherite_leather_flask":12,"create:mechanical_pump":4,"create:fluid_tank":7,"minecraft:dirt":9,"minecraft:spyglass":2,"simpleradio:frequencer":1,"minecraft:loom":2,"minecraft:crafting_table":2,"create:cogwheel":2,"create:fluid_pipe":2,"minecraft:bucket":2,"create:creative_fluid_tank":19,"minecraft:sponge":346,"create:depot":2,"minecraft:granite":3,"minecraft:cake":2},"minecraft:killed":{"tumbleweed:tumbleweed":1,"minecraft:player":1},"minecraft:custom":{"minecraft:time_since_rest":1441152,"minecraft:sprint_one_cm":371048,"minecraft:walk_one_cm":153210,"minecraft:damage_taken":155,"minecraft:drop":87,"minecraft:damage_dealt":204,"exposure:interact_with_lightroom":15,"minecraft:swim_one_cm":681,"minecraft:interact_with_crafting_table":3,"minecraft:player_kills":1,"minecraft:fly_one_cm":72818331,"minecraft:open_chest":39,"minecraft:crouch_one_cm":8828,"minecraft:interact_with_loom":5,"exposure:film_frames_exposed":4,"minecraft:play_time":1441152,"minecraft:sneak_time":61906,"minecraft:walk_under_water_one_cm":87766,"minecraft:jump":4978,"minecraft:time_since_death":1441152,"minecraft:leave_game":33,"minecraft:walk_on_water_one_cm":372135,"minecraft:climb_one_cm":630,"minecraft:total_world_time":1441152,"minecraft:fall_one_cm":6935,"minecraft:horse_one_cm":507}},"DataVersion":3465}