{"stats":{"minecraft:mined":{"minecraft:cactus":54,"minecraft:red_sandstone":2,"minecraft:jungle_leaves":5,"minecraft:crafting_table":2,"scorchful:sand_pile":3,"minecraft:jungle_log":5,"minecraft:dead_bush":6,"minecraft:sand":19,"minecraft:cobblestone":3,"minecraft:stone":20},"minecraft:used":{"farmersdelight:honey_cookie":14,"minecraft:wooden_axe":1,"minecraft:writable_book":1,"minecraft:stone_sword":2,"minecraft:stone_pickaxe":15,"minecraft:wooden_pickaxe":10,"scorchful:cactus_juice":22,"minecraft:stone_axe":34,"minecraft:cobblestone":4,"minecraft:crafting_table":2,"minecraft:jungle_planks":1},"minecraft:killed":{"tumbleweed:tumbleweed":31,"minecraft:rabbit":1},"minecraft:picked_up":{"minecraft:wheat":3,"minecraft:stick":13,"minecraft:crafting_table":2,"minecraft:feather":14,"minecraft:jungle_log":5,"minecraft:sand":15,"minecraft:dead_bush":10,"minecraft:string":5,"minecraft:rabbit_foot":1,"minecraft:bone":6,"minecraft:cactus":117,"minecraft:red_sandstone":2,"minecraft:gold_nugget":2,"minecraft:rabbit_hide":1,"minecraft:iron_ingot":5,"minecraft:gold_ingot":2,"minecraft:emerald":1,"minecraft:rabbit":1,"minecraft:melon_seeds":1,"minecraft:sugar_cane":5,"minecraft:cobblestone":23},"minecraft:crafted":{"scorchful:cactus_juice":10,"minecraft:crafting_table":1,"minecraft:wooden_pickaxe":1,"minecraft:stone_pickaxe":1,"minecraft:wooden_axe":1,"minecraft:stone_sword":1,"minecraft:stone_axe":1,"kubejs:cactus_clump":29,"minecraft:jungle_planks":12},"minecraft:custom":{"minecraft:time_since_rest":32928,"minecraft:walk_one_cm":165952,"minecraft:sprint_one_cm":129252,"minecraft:damage_taken":50,"minecraft:mob_kills":1,"minecraft:damage_dealt":30,"minecraft:fly_one_cm":216675,"minecraft:interact_with_crafting_table":5,"minecraft:crouch_one_cm":184,"minecraft:play_time":32928,"minecraft:sneak_time":319,"minecraft:jump":673,"minecraft:leave_game":2,"minecraft:time_since_death":32928,"minecraft:damage_resisted":20,"minecraft:total_world_time":32928,"minecraft:fall_one_cm":7733,"minecraft:horse_one_cm":602}},"DataVersion":3465}